odoo/addons/ebill_postfinance_stock/README.rst
odoo/addons/ebill_postfinance_stock/__init__.py
odoo/addons/ebill_postfinance_stock/__manifest__.py
odoo/addons/ebill_postfinance_stock/i18n/ebill_postfinance_stock.pot
odoo/addons/ebill_postfinance_stock/messages/invoice-line-stock-yellowbill.jinja
odoo/addons/ebill_postfinance_stock/models/__init__.py
odoo/addons/ebill_postfinance_stock/models/ebill_postfinance_invoice_message.py
odoo/addons/ebill_postfinance_stock/readme/CONTRIBUTORS.rst
odoo/addons/ebill_postfinance_stock/readme/DESCRIPTION.rst
odoo/addons/ebill_postfinance_stock/static/description/icon.png
odoo/addons/ebill_postfinance_stock/static/description/index.html
odoo/addons/ebill_postfinance_stock/tests/__init__.py
odoo/addons/ebill_postfinance_stock/tests/test_ebill_postfinance_message_yb.py
odoo/addons/ebill_postfinance_stock/tests/examples/invoice_qr_yb.xml
odoo14_addon_ebill_postfinance_stock-14.0.1.0.1.dev2.dist-info/METADATA
odoo14_addon_ebill_postfinance_stock-14.0.1.0.1.dev2.dist-info/WHEEL
odoo14_addon_ebill_postfinance_stock-14.0.1.0.1.dev2.dist-info/top_level.txt
odoo14_addon_ebill_postfinance_stock-14.0.1.0.1.dev2.dist-info/RECORD
